jaxnasium/__init__.py
jaxnasium/_environment.py
jaxnasium/_registry.py
jaxnasium/_spaces.py
jaxnasium/_types.py
jaxnasium/_wrappers.py
jaxnasium/_wrappers_ext.py
jaxnasium/algorithms/__init__.py
jaxnasium/algorithms/_algorithm.py
jaxnasium/algorithms/_dqn.py
jaxnasium/algorithms/_ppo.py
jaxnasium/algorithms/_pqn.py
jaxnasium/algorithms/_sac.py
jaxnasium/algorithms/networks/__init__.py
jaxnasium/algorithms/networks/_agent_networks.py
jaxnasium/algorithms/networks/_architectures.py
jaxnasium/algorithms/networks/_input_output.py
jaxnasium/algorithms/utils/__init__.py
jaxnasium/algorithms/utils/_buffer.py
jaxnasium/algorithms/utils/_distributions.py
jaxnasium/algorithms/utils/_initialization.py
jaxnasium/algorithms/utils/_logging.py
jaxnasium/algorithms/utils/_multi_agent.py
jaxnasium/algorithms/utils/_normalization.py
jaxnasium/algorithms/utils/_scan.py
jaxnasium/algorithms/utils/_transition.py
jaxnasium/algorithms/utils/experimental/__init__.py
jaxnasium/algorithms/utils/experimental/_batching.py
jaxnasium/cli/__init__.py
jaxnasium/cli/init.py
jaxnasium/cli/resources/__init__.py
jaxnasium/cli/resources/env_template.py
jaxnasium/cli/resources/train_template.py
jaxnasium/envs/__init__.py
jaxnasium/envs/acrobot.py
jaxnasium/envs/cartpole.py
jaxnasium/envs/continuous_mountain_car.py
jaxnasium/envs/mountain_car.py
jaxnasium/envs/pendulum.py
jaxnasium/py.typed
jaxnasium/tree/__init__.py
jaxnasium/tree/_tree.py
jaxnasium-0.0.27.dist-info/WHEEL
jaxnasium-0.0.27.dist-info/entry_points.txt
jaxnasium-0.0.27.dist-info/METADATA
jaxnasium-0.0.27.dist-info/RECORD
