Metadata-Version: 2.3
Name: jaxnasium
Version: 0.0.27
Summary: A lightweight utility library for reinforcement learning projects in JAX and Equinox.
Author: Koen Ponse
Author-email: Koen Ponse <k.ponse@liacs.leidenuniv.nl>
Requires-Dist: create-rl-app>=0.0.2
Requires-Dist: equinox>=0.12.1,!=0.13.3
Requires-Dist: jax>=0.5.2,!=0.7.0,!=0.7.1
Requires-Dist: distrax>=0.1.5 ; extra == 'algs'
Requires-Dist: optax>=0.2.4 ; extra == 'algs'
Requires-Dist: jax[cuda]>=0.5.2,!=0.7.0,!=0.7.1 ; extra == 'gpu'
Requires-Python: >=3.11
Provides-Extra: algs
Provides-Extra: gpu
